hotglue_tap_sdk/__init__.py
hotglue_tap_sdk/authenticators.py
hotglue_tap_sdk/cli/__init__.py
hotglue_tap_sdk/cli/common_options.py
hotglue_tap_sdk/configuration/__init__.py
hotglue_tap_sdk/configuration/_dict_config.py
hotglue_tap_sdk/exceptions.py
hotglue_tap_sdk/helpers/__init__.py
hotglue_tap_sdk/helpers/_catalog.py
hotglue_tap_sdk/helpers/_classproperty.py
hotglue_tap_sdk/helpers/_compat.py
hotglue_tap_sdk/helpers/_flattening.py
hotglue_tap_sdk/helpers/_schema.py
hotglue_tap_sdk/helpers/_secrets.py
hotglue_tap_sdk/helpers/_simpleeval.py
hotglue_tap_sdk/helpers/_singer.py
hotglue_tap_sdk/helpers/_state.py
hotglue_tap_sdk/helpers/_typing.py
hotglue_tap_sdk/helpers/_util.py
hotglue_tap_sdk/helpers/capabilities.py
hotglue_tap_sdk/helpers/jsonpath.py
hotglue_tap_sdk/io_base.py
hotglue_tap_sdk/mapper.py
hotglue_tap_sdk/mapper_base.py
hotglue_tap_sdk/plugin_base.py
hotglue_tap_sdk/py.typed
hotglue_tap_sdk/sinks/__init__.py
hotglue_tap_sdk/sinks/batch.py
hotglue_tap_sdk/sinks/core.py
hotglue_tap_sdk/sinks/record.py
hotglue_tap_sdk/sinks/sql.py
hotglue_tap_sdk/streams/__init__.py
hotglue_tap_sdk/streams/core.py
hotglue_tap_sdk/streams/graphql.py
hotglue_tap_sdk/streams/rest.py
hotglue_tap_sdk/streams/sql.py
hotglue_tap_sdk/tap_base.py
hotglue_tap_sdk/target_base.py
hotglue_tap_sdk/testing.py
hotglue_tap_sdk/typing.py
hotglue_tap_sdk-1.0.2.dist-info/METADATA
hotglue_tap_sdk-1.0.2.dist-info/WHEEL
hotglue_tap_sdk-1.0.2.dist-info/licenses/LICENSE
hotglue_tap_sdk-1.0.2.dist-info/RECORD
